Workbook

Sheet Quote Template
A1: AUTOMATED HOME/HEAR QUOTE TEMPLATE
A3: CLIENT NAME
A4: ADDRESS LINE 1
A5: CITY, STATE ZIP
A6: INVOICE #
A7: QUOTE DATE
A8: fPROGRAM
A10: TECHNOLOGY CHOICE | B10: TECHNOLOGY | C10: DESCRIPTION | D10: UNIT PRICE | E10: REBATE | F10: TOTAL
A11: Hot Water Heat Pump - A.O. Smith Signature 900 50 Gal | B11: =IFERROR(VLOOKUP($A11,'Data Lists'!$A:$H,2,FALSE),"") -> Hot Water Heat Pump | C11: =IFERROR(VLOOKUP($A11,'Data Lists'!$A:$H,3,FALSE),"") -> AHRI # 217166009 Brand and description: A.O. Smith Signature 900 50-Gallon Hybrid Heat Pump Water Heater Model # HPSN10-50H45DV 2** UEF: 3.8 Tank size: 50 gallons Description of installation labor Disconnect, remove, and replace the existing water heater with an ENERGY STAR heat pump water heater. Disposal of removed equipment. Disconnect existing water and gas or electrical connections and venting, as required. Install the new water heater as specified in this proposal. Set the unit in the existing location. Connect to existing, serviceable water piping, gas or electric supply, temperature and pressure relief piping, and venting if applicable. Start the unit and verify proper operation upon completion. | D11: =IFERROR(VLOOKUP($A11,'Data Lists'!$A:$H,4,FALSE),"") -> 1750 | E11: =IFERROR(VLOOKUP($A11,'Data Lists'!$A:$H,5,FALSE),"") -> -1750 | F11: =IF($A11="","",IFERROR(VLOOKUP($A11,'Data Lists'!$A:$H,6,FALSE),D11+E11)) -> 0
A12: Electrical - Water Heater Only | B12: =IFERROR(VLOOKUP($A12,'Data Lists'!$A:$H,2,FALSE),"") -> Electrical | C12: =IFERROR(VLOOKUP($A12,'Data Lists'!$A:$H,3,FALSE),"") -> Detailed description Materials needed, approximate length of wire: Wires for changing out Water Heater from Gas to Electric Which qualified upgrade install requires electrical wiring: WH Description of labor involved: Electrician will be updating panel and upgrades to electrical because of WH | D12: =IFERROR(VLOOKUP($A12,'Data Lists'!$A:$H,4,FALSE),"") -> 2000 | E12: =IFERROR(VLOOKUP($A12,'Data Lists'!$A:$H,5,FALSE),"") -> -2000 | F12: =IF($A12="","",IFERROR(VLOOKUP($A12,'Data Lists'!$A:$H,6,FALSE),D12+E12)) -> 0
A13: Energy Star HVAC - York 2 Ton Heat Pump System | B13: =IFERROR(VLOOKUP($A13,'Data Lists'!$A:$H,2,FALSE),"") -> Energy Star HVAC | C13: =IFERROR(VLOOKUP($A13,'Data Lists'!$A:$H,3,FALSE),"") -> AHRI - 217016555 York 2 Ton HP ODU R454B. The YC6 models are 16+ SEER2 high-efficiency outdoor HVAC units designed to pair with residential indoor systems for complete home comfort solutions across the U.S. and Canada. ODU: YH624E2S11 AHU: JHE24B5AC2SS1 Heater Kit: S1-8HK16500506 HSPF2 - 8 SEER2 - 16 EER2 - 12 Heating capacity 24000 BTU Cooling capacity 24000 BTU York 2 Ton AHU Description of install labor Our Exclusive 1 Year Installation Warranty Evacuate refrigerant system, removes air and water Ensure proper amount of freon in AC or HP Complete inspection upon completion Remove and dispose used equipment Ensures proper drainage Clean up work area before leaving worksite Sealed connections for greater efficiency Includes County permit WIFI Thermostat 10 year compressor warranty 10 year parts warranty Equipment Pad to stabilize outdoor unit Equipment selection and sizing per our Heating & Cooling load calculations. Honeywell smart thermostat. 5” display comes with Equipment Interface Module for 2 wire operation. Drip pan for air handler/furnace New return air flex install - R-8 foil backed flex New supply air flex install - R-8 foil backed flex New return plenum box made of metal and insulated New supply plenum distribution box made of metal and insulated Standard duct work transition County Permit included Reconnect indoor equipment to existing electrical Reconnect outdoor equipment to existing electrical | D13: =IFERROR(VLOOKUP($A13,'Data Lists'!$A:$H,4,FALSE),"") -> 14000 | E13: =IFERROR(VLOOKUP($A13,'Data Lists'!$A:$H,5,FALSE),"") -> -14000 | F13: =IF($A13="","",IFERROR(VLOOKUP($A13,'Data Lists'!$A:$H,6,FALSE),D13+E13)) -> 0
A14: Attic Insulation - Owens Corning / PINK Next Gen R-38 | B14: =IFERROR(VLOOKUP($A14,'Data Lists'!$A:$H,2,FALSE),"") -> Attic Insulation | C14: =IFERROR(VLOOKUP($A14,'Data Lists'!$A:$H,3,FALSE),"") -> Location of insulation to be installed: Attic Square feet of area to be insulated: 800 ft² Type of Energy Star insulation: PINK Next Gen Owens Corning Batt Fiberglass Corning Current R value: 12.15 Ending R value: 38 | D14: =IFERROR(VLOOKUP($A14,'Data Lists'!$A:$H,4,FALSE),"") -> 1600 | E14: =IFERROR(VLOOKUP($A14,'Data Lists'!$A:$H,5,FALSE),"") -> -1600 | F14: =IF($A14="","",IFERROR(VLOOKUP($A14,'Data Lists'!$A:$H,6,FALSE),D14+E14)) -> 0
A15: Air Seal - Attic Penetrations and Hatch | B15: =IFERROR(VLOOKUP($A15,'Data Lists'!$A:$H,2,FALSE),"") -> Air Seal | C15: =IFERROR(VLOOKUP($A15,'Data Lists'!$A:$H,3,FALSE),"") -> List of each air sealing location: Air seal attic electrical, plumbing, walls and top plate penetrations. Attic hatch cover seal & insulation. Description of labor involved: 1 Day: 2- or 3-hour job | D15: =IFERROR(VLOOKUP($A15,'Data Lists'!$A:$H,4,FALSE),"") -> 1000 | E15: =IFERROR(VLOOKUP($A15,'Data Lists'!$A:$H,5,FALSE),"") -> -1000 | F15: =IF($A15="","",IFERROR(VLOOKUP($A15,'Data Lists'!$A:$H,6,FALSE),D15+E15)) -> 0
B16: =IFERROR(VLOOKUP($A16,'Data Lists'!$A:$H,2,FALSE),"") | C16: =IFERROR(VLOOKUP($A16,'Data Lists'!$A:$H,3,FALSE),"") | D16: =IFERROR(VLOOKUP($A16,'Data Lists'!$A:$H,4,FALSE),"") | E16: =IFERROR(VLOOKUP($A16,'Data Lists'!$A:$H,5,FALSE),"") | F16: =IF($A16="","",IFERROR(VLOOKUP($A16,'Data Lists'!$A:$H,6,FALSE),D16+E16))
B17: =IFERROR(VLOOKUP($A17,'Data Lists'!$A:$H,2,FALSE),"") | C17: =IFERROR(VLOOKUP($A17,'Data Lists'!$A:$H,3,FALSE),"") | D17: =IFERROR(VLOOKUP($A17,'Data Lists'!$A:$H,4,FALSE),"") | E17: =IFERROR(VLOOKUP($A17,'Data Lists'!$A:$H,5,FALSE),"") | F17: =IF($A17="","",IFERROR(VLOOKUP($A17,'Data Lists'!$A:$H,6,FALSE),D17+E17))
B18: =IFERROR(VLOOKUP($A18,'Data Lists'!$A:$H,2,FALSE),"") | C18: =IFERROR(VLOOKUP($A18,'Data Lists'!$A:$H,3,FALSE),"") | D18: =IFERROR(VLOOKUP($A18,'Data Lists'!$A:$H,4,FALSE),"") | E18: =IFERROR(VLOOKUP($A18,'Data Lists'!$A:$H,5,FALSE),"") | F18: =IF($A18="","",IFERROR(VLOOKUP($A18,'Data Lists'!$A:$H,6,FALSE),D18+E18))
B19: =IFERROR(VLOOKUP($A19,'Data Lists'!$A:$H,2,FALSE),"") | C19: =IFERROR(VLOOKUP($A19,'Data Lists'!$A:$H,3,FALSE),"") | D19: =IFERROR(VLOOKUP($A19,'Data Lists'!$A:$H,4,FALSE),"") | E19: =IFERROR(VLOOKUP($A19,'Data Lists'!$A:$H,5,FALSE),"") | F19: =IF($A19="","",IFERROR(VLOOKUP($A19,'Data Lists'!$A:$H,6,FALSE),D19+E19))
B20: =IFERROR(VLOOKUP($A20,'Data Lists'!$A:$H,2,FALSE),"") | C20: =IFERROR(VLOOKUP($A20,'Data Lists'!$A:$H,3,FALSE),"") | D20: =IFERROR(VLOOKUP($A20,'Data Lists'!$A:$H,4,FALSE),"") | E20: =IFERROR(VLOOKUP($A20,'Data Lists'!$A:$H,5,FALSE),"") | F20: =IF($A20="","",IFERROR(VLOOKUP($A20,'Data Lists'!$A:$H,6,FALSE),D20+E20))
B21: =IFERROR(VLOOKUP($A21,'Data Lists'!$A:$H,2,FALSE),"") | C21: =IFERROR(VLOOKUP($A21,'Data Lists'!$A:$H,3,FALSE),"") | D21: =IFERROR(VLOOKUP($A21,'Data Lists'!$A:$H,4,FALSE),"") | E21: =IFERROR(VLOOKUP($A21,'Data Lists'!$A:$H,5,FALSE),"") | F21: =IF($A21="","",IFERROR(VLOOKUP($A21,'Data Lists'!$A:$H,6,FALSE),D21+E21))
B22: =IFERROR(VLOOKUP($A22,'Data Lists'!$A:$H,2,FALSE),"") | C22: =IFERROR(VLOOKUP($A22,'Data Lists'!$A:$H,3,FALSE),"") | D22: =IFERROR(VLOOKUP($A22,'Data Lists'!$A:$H,4,FALSE),"") | E22: =IFERROR(VLOOKUP($A22,'Data Lists'!$A:$H,5,FALSE),"") | F22: =IF($A22="","",IFERROR(VLOOKUP($A22,'Data Lists'!$A:$H,6,FALSE),D22+E22))
B23: =IFERROR(VLOOKUP($A23,'Data Lists'!$A:$H,2,FALSE),"") | C23: =IFERROR(VLOOKUP($A23,'Data Lists'!$A:$H,3,FALSE),"") | D23: =IFERROR(VLOOKUP($A23,'Data Lists'!$A:$H,4,FALSE),"") | E23: =IFERROR(VLOOKUP($A23,'Data Lists'!$A:$H,5,FALSE),"") | F23: =IF($A23="","",IFERROR(VLOOKUP($A23,'Data Lists'!$A:$H,6,FALSE),D23+E23))
B24: =IFERROR(VLOOKUP($A24,'Data Lists'!$A:$H,2,FALSE),"") | C24: =IFERROR(VLOOKUP($A24,'Data Lists'!$A:$H,3,FALSE),"") | D24: =IFERROR(VLOOKUP($A24,'Data Lists'!$A:$H,4,FALSE),"") | E24: =IFERROR(VLOOKUP($A24,'Data Lists'!$A:$H,5,FALSE),"") | F24: =IF($A24="","",IFERROR(VLOOKUP($A24,'Data Lists'!$A:$H,6,FALSE),D24+E24))
A26: REBATE | B26: =SUM(E11:E24) -> -20350
A27: SUBTOTAL | B27: =SUM(D11:D24) -> 20350
A28: SALES TAX | B28: =0 -> 0
A29: TOTAL DUE | B29: =SUM(F11:F24)+B28 -> 0

Sheet Data Lists
A1: Technology Choice | B1: Technology | C1: Description | D1: Unit Price | E1: Rebate | F1: Total | G1: Category | H1: Source | I1: Column1 | J1: Program | L1: Column1 | M1: Column2 | N1: Column3 | O1: Column4 | P1: Column5
A2: Hot Water Heat Pump - A.O. Smith Signature 900 50 Gal | B2: Hot Water Heat Pump | C2: AHRI # 217166009 Brand and description: A.O. Smith Signature 900 50-Gallon Hybrid Heat Pump Water Heater Model # HPSN10-50H45DV 2** UEF: 3.8 Tank size: 50 gallons Description of installation labor Disconnect, remove, and replace the existing water heater with an ENERGY STAR heat pump water heater. Disposal of removed equipment. Disconnect existing water and gas or electrical connections and venting, as required. Install the new water heater as specified in this proposal. Set the unit in the existing location. Connect to existing, serviceable water piping, gas or electric supply, temperature and pressure relief piping, and venting if applicable. Start the unit and verify proper operation upon completion. | D2: 1750 | E2: -1750 | F2: 0 | G2: HEAR / Constant | H2: New Charles McDonald Quote 20260701 + 61 Plainview Dr quote | J2: H.O.M.E. QUOTE
A3: Hot Water Heat Pump - Aerotherm G2 50 Gal | B3: Hot Water Heat Pump | C3: AHRI # 214784826 Brand and description: Aerotherm G2 Model # RE2HP5010PROPH50-T2-RH400 Efficiency: 430 Tank size: 50 Description of installation labor Update gas water heater tank and replace it with an Energy Star Water Heater. Disconnect and remove the existing water heater if applicable Dispose and remove equipment Disconnect existing water and gas or electrical connection and venting, as required Install a new gas or electric water heater as specified in this proposal Set unit in the existing location Connect to existing, serviceable water piping, gas or electric supply, temperature and pressure relief piping, and venting. Startup unit and verify proper operations | D3: 4000 | E3: -1750 | F3: 2240 | G3: HEAR | H3: 11519 Blushing Star Ct quote | J3: H.E.A.R. QUOTE
A4: Electrical - Water Heater Only | B4: Electrical | C4: Detailed description Materials needed, approximate length of wire: Wires for changing out Water Heater from Gas to Electric Which qualified upgrade install requires electrical wiring: WH Description of labor involved: Electrician will be updating panel and upgrades to electrical because of WH | D4: 2000 | E4: -2000 | F4: 0 | G4: HEAR / Electrical | H4: Sawyer quote
A5: Electrical - HVAC and Water Heater | B5: Electrical | C5: Detailed description Materials needed, approximate length of wire: Wires for changing out HVAC and Water Heater from Gas to Electric Which qualified upgrade install requires electrical wiring: HVAC, WH Description of labor involved: Electrician will be updating panel and upgrades to electrical because of WH and HVAC | D5: 2500 | E5: -2500 | F5: 0 | G5: HEAR / Electrical | H5: Jasmine/Samuel quotes
A6: Electrical Panel Upgrade - Main Outside Panel | B6: Electrical Panel | C6: Detailed description: Panel is not installed correctly. The panel box is over the breaker and impacts easy shutoff. Materials needed: New panel box and updated breakers. Specify main panel or subpanel: Main outside panel. Description of labor involved: Electrician will update the panel and breakers as required by the qualified equipment installation. | D6: 3250 | E6: -3250 | F6: 0 | G6: HEAR / Electrical | H6: New Charles McDonald Quote 20260701
A7: Attic Insulation - Owens Corning / PINK Next Gen R-38 | B7: Attic Insulation | C7: Location of insulation to be installed: Attic Square feet of area to be insulated: 800 ft² Type of Energy Star insulation: PINK Next Gen Owens Corning Batt Fiberglass Corning Current R value: 12.15 Ending R value: 38 | D7: 1600 | E7: -1600 | F7: 0 | G7: HEAR / Constant Insulation | H7: Sawyer quote
A8: Attic Insulation - Owens Corning 1,431 SF R-38 | B8: Attic Insulation | C8: Description of insulation Location of insulation to be installed: Attic Square feet of area to be insulated: 1,431 Type of Energy Star insulation: Owens Corning Current R value: 12.15 Ending R value: 38 | D8: 1600 | E8: -1600 | F8: 0 | G8: HEAR / Insulation | H8: 11519 Blushing Star Ct quote
A9: Attic Insulation - CertainTeed R-38 Spray In 1,100 SF | B9: Attic Insulation | C9: Location of insulation to be installed: Attic Square feet of area to be insulated: 1,100 ft² Type of Energy Star insulation: CertainTeed R-38 Spray In Insulation for 1,100 sf area Current R value: 3.75 Ending R value: 49 R Value | D9: 1600 | E9: -1600 | F9: 0 | G9: HEAR / Insulation | H9: 5213 Walnut quote
A10: Crawl Space Insulation and Air Seal - Owens Corning R-19 | B10: Crawl Space Insulation and Air Seal | C10: Owens Corning R-19 Wall Unfaced Fiberglass Batt Insulation 77.5-sq ft (15-in W x 93-in L) R-19 unfaced insulation batt, easy 2x6 wall, floor and crawlspace install. 34 R-Value added per Inch Model #E55P Maximum R-Value -19 Square feet of area to be insulated: 800 ft² | D10: 2000 | E10: -2000 | F10: 0 | G10: HOME / Constant Insulation | H10: Sawyer HOME quote
A11: Crawl Space Insulation and Air Seal - Owens Corning R-19 1,300 SF | B11: Crawl Space Insulation and Air Seal | C11: Owens Corning R-19 Wall Unfaced Fiberglass Batt Insulation 77.5-sq ft (15-in W x 93-in L) R-19 unfaced insulation batt, easy 2x6 wall, floor and crawlspace install 34 R-Value added per Inch Model #E55P Maximum R-Value -19 Area: 1300 sf | D11: 2250 | E11: -2250 | F11: 0 | G11: HOME / Insulation | H11: 6313 Tabor Church Rd quote
A12: Air Seal - Attic Penetrations and Hatch | B12: Air Seal | C12: List of each air sealing location: Air seal attic electrical, plumbing, walls and top plate penetrations. Attic hatch cover seal & insulation. Description of labor involved: 1 Day: 2- or 3-hour job | D12: 1000 | E12: -1000 | F12: 0 | G12: HEAR / Air Seal | H12: Sawyer quote
A13: Heat Pump Dryer - LG DLHC1455W | B13: Heat Pump Dryer | C13: Updating dryer to an Energy Star Heat Pump Dryer Model DLHC1455W | D13: 840 | E13: -840 | F13: 0 | G13: HEAR | H13: 5213 Walnut material list
A14: Energy Star HVAC - York 2 Ton Heat Pump System | B14: Energy Star HVAC | C14: AHRI - 217016555 York 2 Ton HP ODU R454B. The YC6 models are 16+ SEER2 high-efficiency outdoor HVAC units designed to pair with residential indoor systems for complete home comfort solutions across the U.S. and Canada. ODU: YH624E2S11 AHU: JHE24B5AC2SS1 Heater Kit: S1-8HK16500506 HSPF2 - 8 SEER2 - 16 EER2 - 12 Heating capacity 24000 BTU Cooling capacity 24000 BTU York 2 Ton AHU Description of install labor Our Exclusive 1 Year Installation Warranty Evacuate refrigerant system, removes air and water Ensure proper amount of freon in AC or HP Complete inspection upon completion Remove and dispose used equipment Ensures proper drainage Clean up work area before leaving worksite Sealed connections for greater efficiency Includes County permit WIFI Thermostat 10 year compressor warranty 10 year parts warranty Equipment Pad to stabilize outdoor unit Equipment selection and sizing per our Heating & Cooling load calculations. Honeywell smart thermostat. 5” display comes with Equipment Interface Module for 2 wire operation. Drip pan for air handler/furnace New return air flex install - R-8 foil backed flex New supply air flex install - R-8 foil backed flex New return plenum box made of metal and insulated New supply plenum distribution box made of metal and insulated Standard duct work transition County Permit included Reconnect indoor equipment to existing electrical Reconnect outdoor equipment to existing electrical | D14: 14000 | E14: -14000 | F14: 0 | G14: HOME / HVAC | H14: Contractor Quick Reference + Sawyer quote
A15: Energy Star HVAC - York 3 Ton Heat Pump System | B15: Energy Star HVAC | C15: AHRI # 217016556 Outdoor unit Brand and description: York 3 Ton ODU Model # YH636E2S11 HSPF2: 8 SEER2: 16 Heating capacity: 35,000 BTU Cooling capacity: 34,000 BTU Compatible indoor unit Brand and description: York 3 Ton AHU Model # JHE36B5CD2SS1 Description of installation labor Remove the existing split-system HVAC equipment, including the outdoor unit and indoor air handler or furnace, if applicable. Dispose of removed equipment. Install the new ENERGY STAR split-system HVAC equipment specified in this proposal. Set and secure the outdoor unit on the existing pad. Install the indoor air handler or furnace in the existing location. Connect to existing, serviceable ductwork, refrigerant piping, electrical connections, condensate drainage, gas piping if applicable, and thermostat wiring. Evacuate, charge, and start the system in accordance with manufacturer requirements. Verify proper operation upon completion. Includes 1-year installation labor warranty and 10-year compressor and parts warranties. | D15: 15000 | E15: -15000 | F15: 0 | G15: HOME / HVAC | H15: 61 Plainview Dr - Goodew New + Contractor Quick Reference
... A24: Air Seal - Door, Attic and Fan Penetrations | B24: Air Seal | C24: Air sealing locations: Door, attic, and fan. Penetrations and air infiltration addressed: Plumbing, walls, and top-plate penetrations. Product: Sealant. | D24: 1000 | E24: -1000 | F24: 0 | G24: HOME / Air Seal | H24: 61 Plainview Dr - Goodew New
